{
  "activities": [
    {
      "id": "act_santa_cabin_181630",
      "title": "Santa's Cozy Cabin Meet & Greet",
      "description": "A relaxed meet & greet with Santa in his cozy cabin, perfect for family photos and wish lists.",
      "startDateTime": "2026-12-18T16:30:00",
      "endDateTime": "2026-12-18T17:15:00",
      "category": "santa_experience",
      "audience": "families",
      "locationName": "Santa's Cabin – North Village",
      "locationType": "indoor",
      "accessibilityNotes": "Wheelchair-accessible ramp and low photo bench available; flash can be reduced on request.",
      "isActive": true
    },
    {
      "id": "act_santa_storytime_181900",
      "title": "Santa Storytime by the Fire",
      "description": "Join Santa for a cozy storytime featuring classic Christmas tales by the indoor lodge fireplace.",
      "startDateTime": "2026-12-18T19:00:00",
      "endDateTime": "2026-12-18T19:30:00",
      "category": "santa_experience",
      "audience": "families",
      "locationName": "Lodge Fireplace Corner",
      "locationType": "indoor",
      "accessibilityNotes": "Seating reserved for wheelchair users and low-sensory seating available near exits.",
      "isActive": true
    },
    {
      "id": "act_light_northern_181700",
      "title": "Northern Lights Synchronized Show",
      "description": "A choreographed light show set to orchestral holiday music in the main plaza.",
      "startDateTime": "2026-12-18T17:00:00",
      "endDateTime": "2026-12-18T17:20:00",
      "category": "light_show",
      "audience": "families",
      "locationName": "Main Plaza – Light Tree",
      "locationType": "outdoor",
      "accessibilityNotes": "Accessible viewing area with level ground and limited strobe effects.",
      "isActive": true
    },
    {
      "id": "act_light_finale_181930",
      "title": "Winter Aurora Finale Light Show",
      "description": "End your evening with our grand finale of sweeping lights and festive music.",
      "startDateTime": "2026-12-18T19:30:00",
      "endDateTime": "2026-12-18T20:00:00",
      "category": "light_show",
      "audience": "all_ages",
      "locationName": "Riverfront Spectator Lawn",
      "locationType": "outdoor",
      "accessibilityNotes": "Wheelchair risers located at the back of the lawn; assistive listening devices available on request.",
      "isActive": true
    },
    {
      "id": "act_workshop_ornaments_181615",
      "title": "Elf Workshop: Ornament Decorating",
      "description": "Create your own keepsake ornament with help from Santa's crafty elves. All supplies included.",
      "startDateTime": "2026-12-18T16:15:00",
      "endDateTime": "2026-12-18T17:00:00",
      "category": "workshop_craft",
      "audience": "families",
      "locationName": "Elf Workshop Barn – Table A",
      "locationType": "indoor",
      "accessibilityNotes": "Tables at wheelchair-friendly height; fragrance-free glues available.",
      "isActive": true
    },
    {
      "id": "act_workshop_snowflakes_181800",
      "title": "Family Snowflake Craft Lab",
      "description": "Cut, paint, and glitter your own paper snowflakes in this family-friendly craft lab.",
      "startDateTime": "2026-12-18T18:00:00",
      "endDateTime": "2026-12-18T18:45:00",
      "category": "workshop_craft",
      "audience": "families",
      "locationName": "Creative Corner – Indoor Pavilion",
      "locationType": "indoor",
      "accessibilityNotes": "Quiet corner available for guests with sensory needs; reach tools provided.",
      "isActive": true
    },
    {
      "id": "act_music_carolers_182000",
      "title": "Carolers on the Green",
      "description": "Traditional carols performed live by our costumed choir under the sparkling trees.",
      "startDateTime": "2026-12-18T20:00:00",
      "endDateTime": "2026-12-18T20:30:00",
      "category": "live_music",
      "audience": "all_ages",
      "locationName": "Village Green Stage",
      "locationType": "outdoor",
      "accessibilityNotes": "Paved paths and seating area available; moderate amplification used.",
      "isActive": true
    },
    {
      "id": "act_parade_arrival_101730",
      "title": "Santa's Grand Arrival Parade",
      "description": "Watch Santa arrive with his elves, toy soldiers, and marching band in this lively mini-parade.",
      "startDateTime": "2026-12-10T17:30:00",
      "endDateTime": "2026-12-10T18:00:00",
      "category": "show",
      "audience": "families",
      "locationName": "Main Plaza Parade Route",
      "locationType": "outdoor",
      "accessibilityNotes": "Accessible curbside viewing along the North Gate side of the route.",
      "isActive": true
    },
    {
      "id": "act_workshop_gingerbread_171500",
      "title": "Gingerbread House Decorating Workshop",
      "description": "Build and decorate your own gingerbread house with icing, candy, and expert tips.",
      "startDateTime": "2026-12-17T15:00:00",
      "endDateTime": "2026-12-17T16:30:00",
      "category": "workshop_craft",
      "audience": "families",
      "locationName": "Baker's Hall – Kitchen Studio",
      "locationType": "indoor",
      "accessibilityNotes": "Gluten-free gingerbread kits available by request; seating provided.",
      "isActive": true
    },
    {
      "id": "act_music_jazz_171900",
      "title": "Holiday Jazz Trio at the Lodge",
      "description": "Smooth seasonal jazz standards performed live in the warmth of the lodge.",
      "startDateTime": "2026-12-17T19:00:00",
      "endDateTime": "2026-12-17T20:00:00",
      "category": "live_music",
      "audience": "adults",
      "locationName": "Evergreen Lodge – Hearth Room",
      "locationType": "indoor",
      "accessibilityNotes": "Table service available; low lighting, but pathways kept clear.",
      "isActive": true
    },
    {
      "id": "act_train_polar_181600",
      "title": "Polar Express Mini Train Ride",
      "description": "A short, family-friendly train ride around the illuminated village loop.",
      "startDateTime": "2026-12-18T16:00:00",
      "endDateTime": "2026-12-18T16:10:00",
      "category": "other",
      "audience": "all_ages",
      "locationName": "Mini Train Depot – Central Loop",
      "locationType": "mixed",
      "accessibilityNotes": "One accessible carriage available; boarding ramp at depot.",
      "isActive": true
    },
    {
      "id": "act_light_tunnel_191830",
      "title": "Twinkle Tunnel Walkthrough",
      "description": "Stroll through a tunnel of thousands of synchronized twinkling lights.",
      "startDateTime": "2026-12-19T18:30:00",
      "endDateTime": "2026-12-19T19:00:00",
      "category": "light_show",
      "audience": "all_ages",
      "locationName": "Twinkle Tunnel – Riverside Path",
      "locationType": "outdoor",
      "accessibilityNotes": "Smooth, paved path; mild pulsing lights, no rapid strobe.",
      "isActive": true
    },
    {
      "id": "act_workshop_cookies_191600",
      "title": "Kids' Cookie Decorating Party",
      "description": "Children decorate sugar cookies with sprinkles and icing, supervised by our cookie elves.",
      "startDateTime": "2026-12-19T16:00:00",
      "endDateTime": "2026-12-19T16:45:00",
      "category": "workshop_craft",
      "audience": "kids",
      "locationName": "Cookie Corner – Indoor Kitchen",
      "locationType": "indoor",
      "accessibilityNotes": "Nut-free options available; high chairs available on request.",
      "isActive": true
    },
    {
      "id": "act_santa_sensory_110900",
      "title": "Quiet Santa – Sensory-Friendly Visit",
      "description": "A low-sensory Santa visit with dimmed lights, softer sounds, and extended time slots.",
      "startDateTime": "2026-12-11T09:00:00",
      "endDateTime": "2026-12-11T09:30:00",
      "category": "santa_experience",
      "audience": "kids",
      "locationName": "Quiet Room – North Lodge",
      "locationType": "indoor",
      "accessibilityNotes": "Sensory tools available; maximum of 4 families per session; wheelchair accessible.",
      "isActive": true
    },
    {
      "id": "act_light_sensory_110930",
      "title": "Sensory-Friendly Lights Preview",
      "description": "A gentle preview of our light displays with reduced brightness and no loud music.",
      "startDateTime": "2026-12-11T09:30:00",
      "endDateTime": "2026-12-11T10:00:00",
      "category": "light_show",
      "audience": "families",
      "locationName": "Main Plaza – Sensory Path",
      "locationType": "mixed",
      "accessibilityNotes": "No strobe effects; low crowd capacity; seating available along the route.",
      "isActive": true
    },
    {
      "id": "act_show_puppet_201700",
      "title": "Elf & Reindeer Puppet Show",
      "description": "A whimsical puppet show telling the story of Santa's busiest night.",
      "startDateTime": "2026-12-20T17:00:00",
      "endDateTime": "2026-12-20T17:30:00",
      "category": "show",
      "audience": "kids",
      "locationName": "Children's Theater Tent",
      "locationType": "indoor",
      "accessibilityNotes": "Front-row floor seating for kids; space for wheelchairs at the sides.",
      "isActive": true
    }
  ],
  "entrances": [
    {
      "id": "north_gate_accessible",
      "name": "North Gate – Accessible",
      "description": "Primary accessible entrance located nearest to the parking garage and bus stop.",
      "isWheelchairAccessible": true,
      "isMainEntrance": true,
      "mapCoordinates": "47.6101,-122.2015",
      "directions": "From the main parking garage, follow signs to the North Gate ramp entrance. Elevators are available from all parking levels.",
      "notes": "Wheelchair loans and accessibility assistance are coordinated from this gate."
    },
    {
      "id": "south_gate_main",
      "name": "South Gate – Main Plaza",
      "description": "Entrance opening directly into the Main Plaza near the central Christmas tree.",
      "isWheelchairAccessible": true,
      "isMainEntrance": false,
      "mapCoordinates": "47.6095,-122.2010",
      "directions": "Pedestrian access from City Center via Holiday Lane. Follow the lit archway to the South Gate turnstiles.",
      "notes": "Can be crowded during peak arrival times; consider North Gate for a quieter entrance."
    },
    {
      "id": "east_gate_rides",
      "name": "East Gate – Rides Entrance",
      "description": "Entrance closest to the rides and mini train depot.",
      "isWheelchairAccessible": false,
      "isMainEntrance": false,
      "mapCoordinates": "47.6103,-122.1998",
      "directions": "From the overflow parking lot, follow the fenced path along the river to the East Gate.",
      "notes": "Stairs at this entrance; guests using mobility devices should use North or South Gates instead."
    },
    {
      "id": "west_parking_entrance",
      "name": "West Parking Entrance",
      "description": "Secondary entrance adjacent to the surface parking lot, with ramp access.",
      "isWheelchairAccessible": true,
      "isMainEntrance": false,
      "mapCoordinates": "47.6098,-122.2028",
      "directions": "From the West Lot, follow the illuminated pathway to the ticket booth and ramp at the West Entrance.",
      "notes": "Shortest walking distance for guests parking in the West Lot; limited staffing after 9:30 pm."
    }
  ],
  "ticket_types": [
    {
      "id": "general_admission",
      "name": "General Admission",
      "description": "Standard entry to the Christmas attraction for the selected evening, including access to all open walk-through areas, most shows, and general activities.",
      "whatsIncluded": "Includes entry for one guest on a single night, access to main light displays, live music, and general activity areas. Does not include reserved seating, photo packages, or complimentary food and drink.",
      "perks": [
        "Access to main light displays",
        "Access to general seating areas (first-come, first-served)",
        "Access to outdoor live music and roaming entertainment"
      ],
      "includesFreeDrink": false,
      "adultPrice": 45.0,
      "childPrice": 29.0,
      "ticketCategory": "standard",
      "status": "active",
      "imageUrl": "https://www.thelightsofchristmas.com/wp-content/uploads/The-Lights-of-Christmas-tickets-gal-1.jpg",
      "displayOrder": 1
    },
    {
      "id": "vip_holiday_package",
      "name": "VIP Holiday Package",
      "description": "Upgrade your visit with VIP perks including priority entry, reserved viewing for the finale light show, and complimentary seasonal drinks.",
      "whatsIncluded": "Includes VIP entry for one guest on a single night, priority security and entry line, reserved viewing area for the Winter Aurora Finale Light Show, one complimentary holiday cocktail or hot cocoa, and a commemorative lanyard.",
      "perks": [
        "Priority entry at VIP lane",
        "Reserved finale light show viewing area",
        "One complimentary holiday drink (cocktail or hot cocoa)",
        "Commemorative VIP lanyard"
      ],
      "includesFreeDrink": true,
      "adultPrice": 55.0,
      "childPrice": 39.0,
      "ticketCategory": "vip",
      "status": "active",
      "imageUrl": "https://www.funktionevents.co.uk/images/pictures/new/uk/activities/eden/eden-reserved-area-with-vip-drinks-(product-player).jpg",
      "displayOrder": 2
    },
    {
      "id": "family_night_ticket",
      "name": "Family Night Ticket",
      "description": "Discounted admission designed for families, available on select midweek Family Night dates.",
      "whatsIncluded": "Includes admission for one person on designated Family Night evenings, access to all family zones, and participation in family-focused activities.",
      "perks": [
        "Discounted pricing on select dates",
        "Access to Family Night activities and games",
        "Complimentary kids' activity sheet"
      ],
      "includesFreeDrink": false,
      "adultPrice": 30.0,
      "childPrice": 20.0,
      "ticketCategory": "family",
      "status": "active",
      "imageUrl": "https://totsfamily.com/wp-content/uploads/2015/05/10-Ways-to-Have-a-Fun-Summer-with-Your-Kids.jpg",
      "displayOrder": 3
    },
    {
      "id": "sensory_friendly_morning",
      "name": "Sensory-Friendly Morning Session",
      "description": "A specially designed low-sensory visit with reduced noise, softer lighting, and limited capacity, typically offered on select weekend mornings.",
      "whatsIncluded": "Includes admission to the attraction during a designated sensory-friendly morning time slot, with reduced crowd levels, quieter music, and modified light displays.",
      "perks": [
        "Reduced-capacity session",
        "Lower volume music and announcements",
        "Dimmed and static light displays",
        "Access to quiet rooms"
      ],
      "includesFreeDrink": false,
      "adultPrice": 25.0,
      "childPrice": 12.0,
      "ticketCategory": "other",
      "status": "active",
      "imageUrl": "https://ewscripps.brightspotcdn.com/dims4/default/89fed78/2147483647/strip/true/crop/1920x1080+0+0/resize/1280x720!/quality/90/?url=https%3A%2F%2Fmediaassets.wtkr.com%2Ftribune-network%2Ftribwtkr-files-wordpress%2F2019%2F12%2Fdanta.jpg",
      "displayOrder": 4
    },
    {
      "id": "group_evening_discount",
      "name": "Group Evening Ticket (10+ Guests)",
      "description": "Discounted per-person evening admission for groups of 10 or more, ideal for clubs, teams, and extended families.",
      "whatsIncluded": "Includes general admission for one guest as part of an eligible group booking. Group receives a dedicated check-in point and one complimentary group photo download.",
      "perks": [
        "Discounted price for groups of 10+",
        "Dedicated group check-in lane",
        "One complimentary digital group photo"
      ],
      "includesFreeDrink": false,
      "adultPrice": 35.0,
      "childPrice": 0.0,
      "ticketCategory": "group",
      "status": "active",
      "imageUrl": "https://static.wixstatic.com/media/2f9e21_21f5819e36834c84bcf4769278a1a100~mv2.jpg/v1/crop/x_1367,y_0,w_1782,h_2798/fill/w_490,h_769,al_c,q_85,usm_0.66_1.00_0.01/Group%20of%20friends%20celebrating%20Christmas%20a.jpg",
      "displayOrder": 5
    },
    {
      "id": "season_pass",
      "name": "Season Pass",
      "description": "Unlimited visits to the attraction for the entire holiday season, subject to capacity limits.",
      "whatsIncluded": "Includes unlimited general admission for one guest throughout the current holiday season, plus 10% off select food, beverage, and merchandise.",
      "perks": [
        "Unlimited general admission during operating season",
        "10% discount on select concessions",
        "10% discount on select merchandise"
      ],
      "includesFreeDrink": false,
      "adultPrice": 120.0,
      "childPrice": 80.0,
      "ticketCategory": "other",
      "status": "active",
      "imageUrl": "https://pd12m.s3.us-west-2.amazonaws.com/images/92580374-9754-5b4b-9804-63e969b524d9.jpeg",
      "displayOrder": 6
    },
    {
      "id": "twilight_ticket",
      "name": "Twilight Entry Ticket",
      "description": "Arrive earlier and enjoy the transition from dusk to full illumination with a twilight entry ticket.",
      "whatsIncluded": "Includes one-time entry from opening through 7:00 pm, access to all open attractions, and eligibility for same-day light shows.",
      "perks": [
        "Early entry during twilight hours",
        "Access to main attractions before peak crowds"
      ],
      "includesFreeDrink": false,
      "adultPrice": 38.0,
      "childPrice": 24.0,
      "ticketCategory": "standard",
      "status": "active",
      "imageUrl": "https://images.saatchiart.com/saatchi/610793/art/8256689/7321928-XCADYWJF-7.jpg",
      "displayOrder": 7
    },
    {
      "id": "late_night_plus_cocoa",
      "name": "Late Night Ticket + Cocoa",
      "description": "Enjoy a quieter late-night visit and warm up with an included hot cocoa.",
      "whatsIncluded": "Includes admission after 8:30 pm on select nights and one complimentary hot cocoa redeemed at participating stands.",
      "perks": [
        "Admission during late-night hours",
        "One complimentary hot cocoa",
        "Smaller crowds and easier parking"
      ],
      "includesFreeDrink": true,
      "adultPrice": 38.0,
      "childPrice": 22.0,
      "ticketCategory": "other",
      "status": "active",
      "imageUrl": "https://img.ehowcdn.com/630x/photos.demandstudios.com/getty/article/178/232/78373484.jpg",
      "displayOrder": 8
    },
    {
      "id": "santa_photo_bundle",
      "name": "Santa Photo Bundle",
      "description": "Add-on bundle for professional photos with Santa, including digital downloads.",
      "whatsIncluded": "Includes a reserved photo session with Santa and a set of high-resolution digital image downloads, plus a small print package.",
      "perks": [
        "Reserved Santa photo time",
        "High-resolution digital downloads",
        "Two 5x7\" prints"
      ],
      "includesFreeDrink": false,
      "adultPrice": 18.0,
      "childPrice": 0.0,
      "ticketCategory": "other",
      "status": "active",
      "imageUrl": "https://pd12m.s3.us-west-2.amazonaws.com/images/a2f58051-ab1b-5441-80d9-097e3df095a4.jpeg",
      "displayOrder": 9
    },
    {
      "id": "kids_craft_pass",
      "name": "Kids' Craft Workshop Pass",
      "description": "Access pass for one child to participate in designated craft workshops throughout the evening.",
      "whatsIncluded": "Includes entry to up to three kids' craft workshops in a single night, all standard supplies included.",
      "perks": [
        "Up to three craft workshop entries in one night",
        "All basic craft materials included"
      ],
      "includesFreeDrink": false,
      "adultPrice": 0.0,
      "childPrice": 18.0,
      "ticketCategory": "family",
      "status": "active",
      "imageUrl": "https://pd12m.s3.us-west-2.amazonaws.com/images/07fd0884-9531-508a-9397-2aff1ddae6eb.jpeg",
      "displayOrder": 10
    },
    {
      "id": "date_night_duo",
      "name": "Date Night Duo Package",
      "description": "A package tailored for two adults, including admission, reserved seating at a live music set, and a shared dessert.",
      "whatsIncluded": "Includes admission for one adult (must be purchased twice for two guests), reserved seating at a live music performance, and a shared dessert platter for two.",
      "perks": [
        "Reserved seating at one live music set",
        "Shared dessert platter for two",
        "Keepsake ornament for couples"
      ],
      "includesFreeDrink": false,
      "adultPrice": 60.0,
      "childPrice": 0.0,
      "ticketCategory": "vip",
      "status": "active",
      "imageUrl": "https://pd12m.s3.us-west-2.amazonaws.com/images/58ecd4bf-f53f-54df-8e9b-3c7da25fce7a.jpeg",
      "displayOrder": 11
    },
    {
      "id": "weekday_value_pass",
      "name": "Weekday Value Pass",
      "description": "Discounted admission valid on select non-peak weekday nights.",
      "whatsIncluded": "Includes general admission for one guest on eligible weekday dates, with access to standard shows and activities.",
      "perks": [
        "Lower price on select weekdays",
        "All standard general admission inclusions"
      ],
      "includesFreeDrink": false,
      "adultPrice": 32.0,
      "childPrice": 21.0,
      "ticketCategory": "standard",
      "status": "active",
      "imageUrl": "https://admissions.tcu.edu/images/blog/college-selection-process-header-small.jpg",
      "displayOrder": 12
    }
  ],
  "transit_routes": [
    {
      "id": "bus_42_holiday_loop",
      "name": "Bus 42 – Downtown Holiday Loop",
      "mode": "bus",
      "walkingTimeMinutes": 6,
      "serviceStartTime": "06:30",
      "serviceEndTime": "23:15",
      "daysOfWeek": [
        "monday",
        "tuesday",
        "wednesday",
        "thursday",
        "friday",
        "saturday",
        "sunday"
      ],
      "description": "Frequent bus service connecting the downtown transit hub to the attraction's North Gate stop.",
      "detailsUrl": "https://www.citytransit.gov/routes/42",
      "notes": "North Gate stop is directly across from the accessible entrance; increased frequency on Friday and Saturday evenings."
    },
    {
      "id": "bus_15_crosstown",
      "name": "Bus 15 – Crosstown",
      "mode": "bus",
      "walkingTimeMinutes": 12,
      "serviceStartTime": "05:50",
      "serviceEndTime": "21:45",
      "daysOfWeek": [
        "monday",
        "tuesday",
        "wednesday",
        "thursday",
        "friday"
      ],
      "description": "Crosstown route with a stop near the West Parking Entrance, about a 10–12 minute walk.",
      "detailsUrl": "https://www.citytransit.gov/routes/15",
      "notes": "Last evening trips may be crowded; check live tracker for delays."
    },
    {
      "id": "bus_7_park_ride",
      "name": "Bus 7 – Park & Ride Shuttle",
      "mode": "bus",
      "walkingTimeMinutes": 9,
      "serviceStartTime": "15:00",
      "serviceEndTime": "21:30",
      "daysOfWeek": [
        "friday",
        "saturday",
        "sunday"
      ],
      "description": "Shuttle from the regional Park & Ride lot to a stop near the East Gate.",
      "detailsUrl": "https://www.citytransit.gov/routes/7",
      "notes": "Operates only during the holiday season; not all trips are wheelchair accessible."
    },
    {
      "id": "train_north_line",
      "name": "North Line Commuter Train",
      "mode": "train",
      "walkingTimeMinutes": 14,
      "serviceStartTime": "05:30",
      "serviceEndTime": "22:05",
      "daysOfWeek": [
        "monday",
        "tuesday",
        "wednesday",
        "thursday",
        "friday"
      ],
      "description": "Regional commuter rail with a station approximately a 14-minute walk from the attraction.",
      "detailsUrl": "https://www.regionrail.gov/schedules/northline",
      "notes": "Limited late-night departures; check timetable for exact last train times."
    },
    {
      "id": "subway_green_line",
      "name": "Green Line – Festival Station",
      "mode": "subway",
      "walkingTimeMinutes": 8,
      "serviceStartTime": "05:00",
      "serviceEndTime": "00:15",
      "daysOfWeek": [
        "monday",
        "tuesday",
        "wednesday",
        "thursday",
        "friday",
        "saturday"
      ],
      "description": "Subway service with a station at Festival Station, a short walk along a well-lit route.",
      "detailsUrl": "https://www.metrotransit.gov/lines/green",
      "notes": "Elevators available at Festival Station; trains can be crowded immediately after closing time."
    },
    {
      "id": "tram_riverfront",
      "name": "Riverfront Holiday Tram",
      "mode": "tram",
      "walkingTimeMinutes": 5,
      "serviceStartTime": "16:00",
      "serviceEndTime": "22:00",
      "daysOfWeek": [
        "friday",
        "saturday",
        "sunday"
      ],
      "description": "Seasonal tram running along the riverfront with a stop near the South Gate.",
      "detailsUrl": "https://www.citytransit.gov/routes/riverfront-tram",
      "notes": "Open-air cars; dress warmly. Last departure leaves the attraction shortly after closing."
    },
    {
      "id": "ferry_winter_crossing",
      "name": "Winter Crossing Ferry",
      "mode": "ferry",
      "walkingTimeMinutes": 18,
      "serviceStartTime": "07:15",
      "serviceEndTime": "20:30",
      "daysOfWeek": [
        "monday",
        "tuesday",
        "wednesday",
        "thursday",
        "friday"
      ],
      "description": "Scenic ferry route across the river with a dock within walking distance of the attraction.",
      "detailsUrl": "https://www.harbortransit.gov/routes/winter-crossing",
      "notes": "Operates weather permitting; check alerts for cancellations on windy evenings."
    },
    {
      "id": "bus_28_lakeshore",
      "name": "Bus 28 – Lakeshore",
      "mode": "bus",
      "walkingTimeMinutes": 16,
      "serviceStartTime": "06:10",
      "serviceEndTime": "22:10",
      "daysOfWeek": [
        "saturday",
        "sunday"
      ],
      "description": "Weekend-only bus service running along Lakeshore Drive with a stop near the overflow parking.",
      "detailsUrl": "https://www.citytransit.gov/routes/28",
      "notes": "Stop is farther from the main entrances; allow extra time if traveling with young children."
    }
  ],
  "accessible_viewing_areas": [
    {
      "id": "view_main_plaza_light_deck",
      "name": "Main Plaza Light Show Viewing Deck",
      "description": "Raised, gently sloped deck with level surfaces reserved for guests using wheelchairs, mobility devices, or who need step-free viewing of the plaza light shows.",
      "nearestEntranceId": "north_gate_accessible",
      "isWheelchairAccessible": true,
      "seatingType": "mixed",
      "mapCoordinates": "47.6100,-122.2012",
      "notes": "Best spot for the Northern Lights Synchronized Show; arrive 10\u001215 minutes early for guaranteed space."
    },
    {
      "id": "view_riverfront_finale_zone",
      "name": "Riverfront Finale Accessible Zone",
      "description": "Designated accessible viewing area along the riverfront lawn with unobstructed sightlines to the Winter Aurora Finale Light Show.",
      "nearestEntranceId": "south_gate_main",
      "isWheelchairAccessible": true,
      "seatingType": "mixed",
      "mapCoordinates": "47.6096,-122.2007",
      "notes": "Portable chairs available on request; mild sound levels with option to borrow ear defenders from staff."
    },
    {
      "id": "view_parade_north_curb",
      "name": "North Gate Parade Curbside Area",
      "description": "Level curbside zone along the parade route, reserved for wheelchair users and guests with limited mobility during Santa's Grand Arrival Parade.",
      "nearestEntranceId": "north_gate_accessible",
      "isWheelchairAccessible": true,
      "seatingType": "standing",
      "mapCoordinates": "47.6102,-122.2016",
      "notes": "Marked with blue pavement decals; companions should stand behind the marked line to preserve front-row access."
    },
    {
      "id": "view_lodge_music_corner",
      "name": "Evergreen Lodge Music Corner",
      "description": "Indoor corner near the Hearth Room stage with space for wheelchairs and a limited number of accessible-height seats for live music sets.",
      "nearestEntranceId": "west_parking_entrance",
      "isWheelchairAccessible": true,
      "seatingType": "seated",
      "mapCoordinates": "47.6099,-122.2023",
      "notes": "Recommended for guests who prefer a quieter environment; closest restrooms are also accessible."
    }
  ],
  "cart_items": [
    {
      "id": "cartitem_general_2adults",
      "cartId": "cart_example_general",
      "itemType": "ticket_type",
      "sessionId": "",
      "ticketTypeId": "general_admission",
      "ticketSelections": [
        {
          "category": "adult",
          "quantity": 2,
          "unitPrice": 45.0
        }
      ],
      "addOnIds": [],
      "lineTotal": 90.0,
      "description": "General Admission \u0013 2 Adults"
    },
    {
      "id": "cartitem_vip_2adults",
      "cartId": "cart_example_vip",
      "itemType": "ticket_type",
      "sessionId": "",
      "ticketTypeId": "vip_holiday_package",
      "ticketSelections": [
        {
          "category": "adult",
          "quantity": 2,
          "unitPrice": 55.0
        }
      ],
      "addOnIds": [],
      "lineTotal": 110.0,
      "description": "VIP Holiday Package \u0013 2 Adults (includes complimentary holiday drink)"
    },
    {
      "id": "cartitem_familynight_2a2c",
      "cartId": "cart_example_familynight",
      "itemType": "ticket_type",
      "sessionId": "",
      "ticketTypeId": "family_night_ticket",
      "ticketSelections": [
        {
          "category": "adult",
          "quantity": 2,
          "unitPrice": 30.0
        },
        {
          "category": "child",
          "quantity": 2,
          "unitPrice": 20.0
        }
      ],
      "addOnIds": [],
      "lineTotal": 100.0,
      "description": "Family Night Ticket \u0013 2 Adults, 2 Children"
    },
    {
      "id": "cartitem_sensory_1a1c",
      "cartId": "cart_example_sensory",
      "itemType": "ticket_type",
      "sessionId": "",
      "ticketTypeId": "sensory_friendly_morning",
      "ticketSelections": [
        {
          "category": "adult",
          "quantity": 1,
          "unitPrice": 25.0
        },
        {
          "category": "child",
          "quantity": 1,
          "unitPrice": 12.0
        }
      ],
      "addOnIds": [],
      "lineTotal": 37.0,
      "description": "Sensory-Friendly Morning Session \u0013 1 Adult, 1 Child"
    },
    {
      "id": "cartitem_group_15",
      "cartId": "cart_example_group",
      "itemType": "ticket_type",
      "sessionId": "",
      "ticketTypeId": "group_evening_discount",
      "ticketSelections": [
        {
          "category": "adult",
          "quantity": 15,
          "unitPrice": 35.0
        }
      ],
      "addOnIds": [],
      "lineTotal": 525.0,
      "description": "Group Evening Ticket (10+ Guests) \u0013 15 Guests"
    },
    {
      "id": "cartitem_session_family_2a2c",
      "cartId": "cart_example_session_family",
      "itemType": "session_ticket",
      "sessionId": "session_family_night_2026_12_18_1730",
      "ticketTypeId": "",
      "ticketSelections": [
        {
          "category": "adult",
          "quantity": 2,
          "unitPrice": 30.0
        },
        {
          "category": "child",
          "quantity": 2,
          "unitPrice": 20.0
        }
      ],
      "addOnIds": [],
      "lineTotal": 100.0,
      "description": "Family Night 12/18 5:30 pm \u0013 2 Adults, 2 Children"
    }
  ],
  "sessions": [
    {
      "id": "session_family_night_2026_12_10_1700",
      "name": "Family Night \u0013 5:00 pm",
      "eventType": "family_night",
      "startDateTime": "2026-12-10T17:00:00",
      "endDateTime": "2026-12-10T21:00:00",
      "audience": "families",
      "isSensoryFriendly": false,
      "isFamilyNight": true,
      "baseAdultPrice": 28.0,
      "baseChildPrice": 18.0,
      "locationName": "Main Entry \u0013 North & South Gates",
      "notes": "Standard Family Night with full sound and lighting; some shows include mild strobe effects.",
      "labels": [
        "Family Night",
        "Value Night"
      ],
      "maxCapacity": 1800,
      "isActive": true,
      "addOnIds": [],
      "remainingCapacity": 1800
    },
    {
      "id": "session_family_night_2026_12_12_1730",
      "name": "Family Night \u0013 5:30 pm (Best Value)",
      "eventType": "family_night",
      "startDateTime": "2026-12-12T17:30:00",
      "endDateTime": "2026-12-12T21:30:00",
      "audience": "families",
      "isSensoryFriendly": false,
      "isFamilyNight": true,
      "baseAdultPrice": 26.0,
      "baseChildPrice": 16.0,
      "locationName": "Main Entry \u0013 North Gate",
      "notes": "Best-value Family Night pricing; recommended for budget-conscious families.",
      "labels": [
        "Family Night",
        "Best Value"
      ],
      "maxCapacity": 1700,
      "isActive": true,
      "addOnIds": [],
      "remainingCapacity": 1700
    },
    {
      "id": "session_family_night_2026_12_15_1800",
      "name": "Family Night \u0013 6:00 pm",
      "eventType": "family_night",
      "startDateTime": "2026-12-15T18:00:00",
      "endDateTime": "2026-12-15T22:00:00",
      "audience": "families",
      "isSensoryFriendly": false,
      "isFamilyNight": true,
      "baseAdultPrice": 29.0,
      "baseChildPrice": 19.0,
      "locationName": "Main Entry \u0013 South Gate",
      "notes": "Arrive early to enjoy pre-show carolers in the Main Plaza.",
      "labels": [
        "Family Night"
      ],
      "maxCapacity": 1800,
      "isActive": true,
      "addOnIds": [],
      "remainingCapacity": 1800
    },
    {
      "id": "session_family_night_2026_12_18_1730",
      "name": "Family Night \u0013 5:30 pm",
      "eventType": "family_night",
      "startDateTime": "2026-12-18T17:30:00",
      "endDateTime": "2026-12-18T21:30:00",
      "audience": "families",
      "isSensoryFriendly": false,
      "isFamilyNight": true,
      "baseAdultPrice": 30.0,
      "baseChildPrice": 20.0,
      "locationName": "Main Entry \u0013 North Gate",
      "notes": "Includes access to the Winter Aurora Finale Light Show; may sell out early.",
      "labels": [
        "Family Night",
        "Popular"
      ],
      "maxCapacity": 1900,
      "isActive": true,
      "addOnIds": [
        "addon_family_photo_2026_12_18",
        "addon_cocoa_bundle_2026_12_18"
      ],
      "remainingCapacity": 1899
    },
    {
      "id": "session_family_night_2026_12_20_1700",
      "name": "Family Night \u0013 5:00 pm (Weekend)",
      "eventType": "family_night",
      "startDateTime": "2026-12-20T17:00:00",
      "endDateTime": "2026-12-20T21:00:00",
      "audience": "families",
      "isSensoryFriendly": false,
      "isFamilyNight": true,
      "baseAdultPrice": 32.0,
      "baseChildPrice": 22.0,
      "locationName": "Main Entry \u0013 North & South Gates",
      "notes": "Weekend Family Night with extended live music schedule and extra crowd control measures.",
      "labels": [
        "Family Night",
        "Weekend"
      ],
      "maxCapacity": 2000,
      "isActive": true,
      "addOnIds": [],
      "remainingCapacity": 2000
    },
    {
      "id": "session_sensory_2026_12_11_0900",
      "name": "Sensory-Friendly Morning \u0013 Fri 9:00 am",
      "eventType": "sensory_friendly",
      "startDateTime": "2026-12-11T09:00:00",
      "endDateTime": "2026-12-11T10:00:00",
      "audience": "kids",
      "isSensoryFriendly": true,
      "isFamilyNight": false,
      "baseAdultPrice": 25.0,
      "baseChildPrice": 12.0,
      "locationName": "Quiet Morning Entry \u0013 North Gate",
      "notes": "Reduced capacity with lower sound and dimmed, static lights; ideal for younger visitors.",
      "labels": [
        "Sensory-Friendly",
        "Weekday"
      ],
      "maxCapacity": 250,
      "isActive": true,
      "addOnIds": [
        "addon_quiet_kit_2026_12_11"
      ],
      "remainingCapacity": 250
    },
    {
      "id": "session_sensory_2026_12_12_0900",
      "name": "Sensory-Friendly Morning \u0013 Sat 9:00 am",
      "eventType": "sensory_friendly",
      "startDateTime": "2026-12-12T09:00:00",
      "endDateTime": "2026-12-12T10:00:00",
      "audience": "families",
      "isSensoryFriendly": true,
      "isFamilyNight": false,
      "baseAdultPrice": 25.0,
      "baseChildPrice": 12.0,
      "locationName": "Quiet Morning Entry \u0013 North Gate",
      "notes": "First Saturday sensory-friendly time slot; lowest crowds and easiest parking.",
      "labels": [
        "Sensory-Friendly",
        "Low Capacity"
      ],
      "maxCapacity": 300,
      "isActive": true,
      "addOnIds": [
        "addon_sensory_parking_2026_12_12_0900"
      ],
      "remainingCapacity": 300
    },
    {
      "id": "session_sensory_2026_12_12_0945",
      "name": "Sensory-Friendly Morning \u0013 Sat 9:45 am",
      "eventType": "sensory_friendly",
      "startDateTime": "2026-12-12T09:45:00",
      "endDateTime": "2026-12-12T10:45:00",
      "audience": "families",
      "isSensoryFriendly": true,
      "isFamilyNight": false,
      "baseAdultPrice": 25.0,
      "baseChildPrice": 12.0,
      "locationName": "Quiet Morning Entry \u0013 North Gate",
      "notes": "Second Saturday sensory-friendly session; similar experience to 9:00 am with slightly higher attendance.",
      "labels": [
        "Sensory-Friendly"
      ],
      "maxCapacity": 320,
      "isActive": true,
      "addOnIds": [],
      "remainingCapacity": 320
    },
    {
      "id": "session_sensory_2026_12_19_0900",
      "name": "Sensory-Friendly Morning \u0013 Sat 9:00 am",
      "eventType": "sensory_friendly",
      "startDateTime": "2026-12-19T09:00:00",
      "endDateTime": "2026-12-19T10:00:00",
      "audience": "families",
      "isSensoryFriendly": true,
      "isFamilyNight": false,
      "baseAdultPrice": 25.0,
      "baseChildPrice": 12.0,
      "locationName": "Quiet Morning Entry \u0013 North Gate",
      "notes": "Includes optional quiet Santa meet-and-greet; very limited capacity.",
      "labels": [
        "Sensory-Friendly",
        "Limited Availability"
      ],
      "maxCapacity": 260,
      "isActive": true,
      "addOnIds": [],
      "remainingCapacity": 260
    },
    {
      "id": "session_sensory_2026_12_19_0930",
      "name": "Sensory-Friendly Morning \u0013 Sat 9:30 am",
      "eventType": "sensory_friendly",
      "startDateTime": "2026-12-19T09:30:00",
      "endDateTime": "2026-12-19T10:30:00",
      "audience": "families",
      "isSensoryFriendly": true,
      "isFamilyNight": false,
      "baseAdultPrice": 25.0,
      "baseChildPrice": 13.0,
      "locationName": "Quiet Morning Entry \u0013 North Gate",
      "notes": "Similar to other sensory-friendly sessions with slightly higher child pricing due to added activities.",
      "labels": [
        "Sensory-Friendly"
      ],
      "maxCapacity": 320,
      "isActive": true,
      "addOnIds": [],
      "remainingCapacity": 320
    },
    {
      "id": "session_group_2026_12_11_2015",
      "name": "Group Evening \u0013 Fri 8:15 pm",
      "eventType": "group_only",
      "startDateTime": "2026-12-11T20:15:00",
      "endDateTime": "2026-12-11T22:30:00",
      "audience": "all_ages",
      "isSensoryFriendly": false,
      "isFamilyNight": false,
      "baseAdultPrice": 30.0,
      "baseChildPrice": 0.0,
      "locationName": "Group Check-in \u0013 West Parking Entrance",
      "notes": "Available exclusively for pre-booked groups of 10+; includes standard light shows and live music.",
      "labels": [
        "Group Discount",
        "After 8 pm"
      ],
      "maxCapacity": 600,
      "isActive": true,
      "addOnIds": [],
      "remainingCapacity": 600
    },
    {
      "id": "session_group_2026_12_11_2045",
      "name": "Group Evening \u0013 Fri 8:45 pm (Best Deal)",
      "eventType": "group_only",
      "startDateTime": "2026-12-11T20:45:00",
      "endDateTime": "2026-12-11T23:00:00",
      "audience": "all_ages",
      "isSensoryFriendly": false,
      "isFamilyNight": false,
      "baseAdultPrice": 28.0,
      "baseChildPrice": 0.0,
      "locationName": "Group Check-in \u0013 West Parking Entrance",
      "notes": "Cheapest group price per person after 8:00 pm; ideal for large parties.",
      "labels": [
        "Group Discount",
        "Best Deal",
        "After 8 pm"
      ],
      "maxCapacity": 650,
      "isActive": true,
      "addOnIds": [
        "addon_group_hot_cocoa_2026_12_11_2045"
      ],
      "remainingCapacity": 650
    },
    {
      "id": "session_group_2026_12_18_2030",
      "name": "Group Evening \u0013 Fri 8:30 pm",
      "eventType": "group_only",
      "startDateTime": "2026-12-18T20:30:00",
      "endDateTime": "2026-12-18T23:00:00",
      "audience": "all_ages",
      "isSensoryFriendly": false,
      "isFamilyNight": false,
      "baseAdultPrice": 32.0,
      "baseChildPrice": 0.0,
      "locationName": "Group Check-in \u0013 West Parking Entrance",
      "notes": "Includes extended hours and finale light show; slightly higher rate due to peak demand.",
      "labels": [
        "Group Discount",
        "After 8 pm"
      ],
      "maxCapacity": 700,
      "isActive": true,
      "addOnIds": [
        "addon_group_cookie_platter_2026_12_18"
      ],
      "remainingCapacity": 700
    },
    {
      "id": "session_general_2026_12_17_1800",
      "name": "General Evening Session \u0013 6:00 pm",
      "eventType": "general_session",
      "startDateTime": "2026-12-17T18:00:00",
      "endDateTime": "2026-12-17T22:00:00",
      "audience": "all_ages",
      "isSensoryFriendly": false,
      "isFamilyNight": false,
      "baseAdultPrice": 45.0,
      "baseChildPrice": 29.0,
      "locationName": "Main Entry \u0013 North & South Gates",
      "notes": "Standard evening visit with access to all general admission areas and shows.",
      "labels": [
        "General Admission",
        "Most Popular"
      ],
      "maxCapacity": 2200,
      "isActive": true,
      "addOnIds": [],
      "remainingCapacity": 2200
    },
    {
      "id": "session_late_night_2026_12_17_2030",
      "name": "Late Night Session \u0013 8:30 pm + Cocoa",
      "eventType": "other",
      "startDateTime": "2026-12-17T20:30:00",
      "endDateTime": "2026-12-17T23:00:00",
      "audience": "all_ages",
      "isSensoryFriendly": false,
      "isFamilyNight": false,
      "baseAdultPrice": 38.0,
      "baseChildPrice": 22.0,
      "locationName": "Main Entry \u0013 South Gate",
      "notes": "Late-night entry with smaller crowds; includes complimentary cocoa at participating stands.",
      "labels": [
        "Late Night",
        "Includes Free Cocoa"
      ],
      "maxCapacity": 900,
      "isActive": true,
      "addOnIds": [],
      "remainingCapacity": 900
    }
  ],
  "group_session_options": [
    {
      "id": "groupopt_2026_12_11_2015_standard",
      "sessionId": "session_group_2026_12_11_2015",
      "name": "Group Evening – Fri Dec 11, 8:15 pm",
      "startDateTime": "2026-12-11T20:15:00",
      "endDateTime": "2026-12-11T22:30:00",
      "minGroupSize": 10,
      "maxGroupSize": 40,
      "pricePerPerson": 30.0,
      "hasGroupDiscount": true,
      "badges": [
        "Group Discount",
        "Friday Night"
      ],
      "paymentMethodsAvailable": [
        "credit_card",
        "invoice_later"
      ],
      "isActive": true
    },
    {
      "id": "groupopt_2026_12_11_2045_bestdeal",
      "sessionId": "session_group_2026_12_11_2045",
      "name": "Group Evening – Fri Dec 11, 8:45 pm (Best Deal)",
      "startDateTime": "2026-12-11T20:45:00",
      "endDateTime": "2026-12-11T23:00:00",
      "minGroupSize": 10,
      "maxGroupSize": 60,
      "pricePerPerson": 28.0,
      "hasGroupDiscount": true,
      "badges": [
        "Group Discount",
        "Best Deal",
        "After 8 pm"
      ],
      "paymentMethodsAvailable": [
        "credit_card",
        "pay_on_arrival",
        "invoice_later"
      ],
      "isActive": true
    },
    {
      "id": "groupopt_2026_12_18_2030_standard",
      "sessionId": "session_group_2026_12_18_2030",
      "name": "Group Evening – Fri Dec 18, 8:30 pm",
      "startDateTime": "2026-12-18T20:30:00",
      "endDateTime": "2026-12-18T23:00:00",
      "minGroupSize": 10,
      "maxGroupSize": 80,
      "pricePerPerson": 32.0,
      "hasGroupDiscount": true,
      "badges": [
        "Group Discount",
        "After 8 pm"
      ],
      "paymentMethodsAvailable": [
        "credit_card",
        "pay_on_arrival"
      ],
      "isActive": true
    },
    {
      "id": "groupopt_2026_12_17_1800_earlygroup",
      "sessionId": "session_general_2026_12_17_1800",
      "name": "Early Evening Group – Thu Dec 17, 6:00 pm",
      "startDateTime": "2026-12-17T18:00:00",
      "endDateTime": "2026-12-17T22:00:00",
      "minGroupSize": 15,
      "maxGroupSize": 100,
      "pricePerPerson": 34.0,
      "hasGroupDiscount": true,
      "badges": [
        "Group Discount",
        "Weeknight"
      ],
      "paymentMethodsAvailable": [
        "credit_card"
      ],
      "isActive": true
    },
    {
      "id": "groupopt_2026_12_20_1700_nodiscount",
      "sessionId": "session_family_night_2026_12_20_1700",
      "name": "Family Night Group Hold – Sun Dec 20, 5:00 pm",
      "startDateTime": "2026-12-20T17:00:00",
      "endDateTime": "2026-12-20T21:00:00",
      "minGroupSize": 10,
      "maxGroupSize": 50,
      "pricePerPerson": 32.0,
      "hasGroupDiscount": false,
      "badges": [],
      "paymentMethodsAvailable": [
        "credit_card",
        "invoice_later"
      ],
      "isActive": true
    }
  ],
  "session_addons": [
    {
      "id": "addon_family_photo_2026_12_18",
      "sessionId": "session_family_night_2026_12_18_1730",
      "name": "Family Photo with Santa",
      "description": "Reserved time slot for a professional family photo with Santa, including a digital download package.",
      "price": 25.0,
      "defaultSelected": false,
      "isActive": true
    },
    {
      "id": "addon_cocoa_bundle_2026_12_18",
      "sessionId": "session_family_night_2026_12_18_1730",
      "name": "Cocoa & Cookie Bundle",
      "description": "Four hot cocoas and four decorated cookies, ready for pickup at the Main Plaza cocoa stand.",
      "price": 18.0,
      "defaultSelected": false,
      "isActive": true
    },
    {
      "id": "addon_sensory_parking_2026_12_12_0900",
      "sessionId": "session_sensory_2026_12_12_0900",
      "name": "Prepaid Parking – Sensory Morning",
      "description": "Discounted prepaid parking in the North Garage for the 9:00 am sensory-friendly session.",
      "price": 5.0,
      "defaultSelected": true,
      "isActive": true
    },
    {
      "id": "addon_quiet_kit_2026_12_11",
      "sessionId": "session_sensory_2026_12_11_0900",
      "name": "Sensory Support Kit Rental",
      "description": "Includes noise-reducing headphones, fidget tools, and a visual schedule card for the morning.",
      "price": 3.0,
      "defaultSelected": false,
      "isActive": true
    },
    {
      "id": "addon_group_hot_cocoa_2026_12_11_2045",
      "sessionId": "session_group_2026_12_11_2045",
      "name": "Group Hot Cocoa Vouchers",
      "description": "One small hot cocoa per guest, redeemable at any cocoa stand during your group visit.",
      "price": 4.0,
      "defaultSelected": false,
      "isActive": true
    },
    {
      "id": "addon_group_cookie_platter_2026_12_18",
      "sessionId": "session_group_2026_12_18_2030",
      "name": "Holiday Cookie Platters",
      "description": "Assorted holiday cookie platters sized for approximately 10 guests each.",
      "price": 22.0,
      "defaultSelected": false,
      "isActive": true
    }
  ],
  "session_ticket_prices": [
    {
      "id": "stp_family_2026_12_10_adult",
      "sessionId": "session_family_night_2026_12_10_1700",
      "category": "adult",
      "price": 28.0,
      "description": "Adult ticket (ages 13+)",
      "minAge": 13,
      "maxAge": null,
      "currency": "USD"
    },
    {
      "id": "stp_family_2026_12_10_child",
      "sessionId": "session_family_night_2026_12_10_1700",
      "category": "child",
      "price": 18.0,
      "description": "Child ticket (ages 3–12)",
      "minAge": 3,
      "maxAge": 12,
      "currency": "USD"
    },
    {
      "id": "stp_family_2026_12_12_1730_adult",
      "sessionId": "session_family_night_2026_12_12_1730",
      "category": "adult",
      "price": 26.0,
      "description": "Adult ticket (ages 13+)",
      "minAge": 13,
      "maxAge": null,
      "currency": "USD"
    },
    {
      "id": "stp_family_2026_12_12_1730_child",
      "sessionId": "session_family_night_2026_12_12_1730",
      "category": "child",
      "price": 16.0,
      "description": "Child ticket (ages 3–12)",
      "minAge": 3,
      "maxAge": 12,
      "currency": "USD"
    },
    {
      "id": "stp_family_2026_12_15_1800_adult",
      "sessionId": "session_family_night_2026_12_15_1800",
      "category": "adult",
      "price": 29.0,
      "description": "Adult ticket (ages 13+)",
      "minAge": 13,
      "maxAge": null,
      "currency": "USD"
    },
    {
      "id": "stp_family_2026_12_15_1800_child",
      "sessionId": "session_family_night_2026_12_15_1800",
      "category": "child",
      "price": 19.0,
      "description": "Child ticket (ages 3–12)",
      "minAge": 3,
      "maxAge": 12,
      "currency": "USD"
    },
    {
      "id": "stp_family_2026_12_18_1730_adult",
      "sessionId": "session_family_night_2026_12_18_1730",
      "category": "adult",
      "price": 30.0,
      "description": "Adult ticket (ages 13+)",
      "minAge": 13,
      "maxAge": null,
      "currency": "USD"
    },
    {
      "id": "stp_family_2026_12_18_1730_child",
      "sessionId": "session_family_night_2026_12_18_1730",
      "category": "child",
      "price": 20.0,
      "description": "Child ticket (ages 3–12)",
      "minAge": 3,
      "maxAge": 12,
      "currency": "USD"
    },
    {
      "id": "stp_family_2026_12_20_1700_adult",
      "sessionId": "session_family_night_2026_12_20_1700",
      "category": "adult",
      "price": 32.0,
      "description": "Adult ticket (ages 13+)",
      "minAge": 13,
      "maxAge": null,
      "currency": "USD"
    },
    {
      "id": "stp_family_2026_12_20_1700_child",
      "sessionId": "session_family_night_2026_12_20_1700",
      "category": "child",
      "price": 22.0,
      "description": "Child ticket (ages 3–12)",
      "minAge": 3,
      "maxAge": 12,
      "currency": "USD"
    },
    {
      "id": "stp_sensory_2026_12_11_0900_adult",
      "sessionId": "session_sensory_2026_12_11_0900",
      "category": "adult",
      "price": 25.0,
      "description": "Adult ticket (ages 13+)",
      "minAge": 13,
      "maxAge": null,
      "currency": "USD"
    },
    {
      "id": "stp_sensory_2026_12_11_0900_child",
      "sessionId": "session_sensory_2026_12_11_0900",
      "category": "child",
      "price": 12.0,
      "description": "Child ticket (ages 3–12)",
      "minAge": 3,
      "maxAge": 12,
      "currency": "USD"
    },
    {
      "id": "stp_sensory_2026_12_12_0900_adult",
      "sessionId": "session_sensory_2026_12_12_0900",
      "category": "adult",
      "price": 25.0,
      "description": "Adult ticket (ages 13+)",
      "minAge": 13,
      "maxAge": null,
      "currency": "USD"
    },
    {
      "id": "stp_sensory_2026_12_12_0900_child",
      "sessionId": "session_sensory_2026_12_12_0900",
      "category": "child",
      "price": 12.0,
      "description": "Child ticket (ages 3–12)",
      "minAge": 3,
      "maxAge": 12,
      "currency": "USD"
    },
    {
      "id": "stp_sensory_2026_12_12_0945_adult",
      "sessionId": "session_sensory_2026_12_12_0945",
      "category": "adult",
      "price": 25.0,
      "description": "Adult ticket (ages 13+)",
      "minAge": 13,
      "maxAge": null,
      "currency": "USD"
    },
    {
      "id": "stp_sensory_2026_12_12_0945_child",
      "sessionId": "session_sensory_2026_12_12_0945",
      "category": "child",
      "price": 12.0,
      "description": "Child ticket (ages 3–12)",
      "minAge": 3,
      "maxAge": 12,
      "currency": "USD"
    },
    {
      "id": "stp_sensory_2026_12_19_0900_adult",
      "sessionId": "session_sensory_2026_12_19_0900",
      "category": "adult",
      "price": 25.0,
      "description": "Adult ticket (ages 13+)",
      "minAge": 13,
      "maxAge": null,
      "currency": "USD"
    },
    {
      "id": "stp_sensory_2026_12_19_0900_child",
      "sessionId": "session_sensory_2026_12_19_0900",
      "category": "child",
      "price": 12.0,
      "description": "Child ticket (ages 3–12)",
      "minAge": 3,
      "maxAge": 12,
      "currency": "USD"
    },
    {
      "id": "stp_sensory_2026_12_19_0930_adult",
      "sessionId": "session_sensory_2026_12_19_0930",
      "category": "adult",
      "price": 25.0,
      "description": "Adult ticket (ages 13+)",
      "minAge": 13,
      "maxAge": null,
      "currency": "USD"
    },
    {
      "id": "stp_sensory_2026_12_19_0930_child",
      "sessionId": "session_sensory_2026_12_19_0930",
      "category": "child",
      "price": 13.0,
      "description": "Child ticket (ages 3–12)",
      "minAge": 3,
      "maxAge": 12,
      "currency": "USD"
    }
  ],
  "_metadata": {
    "baselineDate": "2026-03-03",
    "generatedAt": "2026-03-03T04:02:22.902378"
  }
}